MANIFEST.in
setup.py
greenhouse/__init__.py
greenhouse/backdoor.py
greenhouse/compat.py
greenhouse/poller.py
greenhouse/pool.py
greenhouse/scheduler.py
greenhouse/util.py
greenhouse.egg-info/PKG-INFO
greenhouse.egg-info/SOURCES.txt
greenhouse.egg-info/dependency_links.txt
greenhouse.egg-info/requires.txt
greenhouse.egg-info/top_level.txt
greenhouse/emulation/__init__.py
greenhouse/emulation/dns.py
greenhouse/emulation/fcntl.py
greenhouse/emulation/os.py
greenhouse/emulation/select.py
greenhouse/emulation/signal.py
greenhouse/emulation/socket.py
greenhouse/emulation/ssl.py
greenhouse/emulation/threading.py
greenhouse/emulation/zmq.py
greenhouse/ext/__init__.py
greenhouse/ext/dns.py
greenhouse/ext/psycopg2.py
greenhouse/ext/zmq.py
greenhouse/io/__init__.py
greenhouse/io/descriptor.py
greenhouse/io/files.py
greenhouse/io/ipc.py
greenhouse/io/sockets.py
greenhouse/io/ssl.py