Metadata-Version: 1.1
Name: greenhouse
Version: 2.1.11
Summary: An I/O parallelism library making use of coroutines
Home-page: http://github.com/teepark/greenhouse
Author: Travis Parker
Author-email: travis.parker@gmail.com
License: BSD
Platform: UNKNOWN
Classifier: Development Status :: 5 - Production/Stable
Classifier: Intended Audience :: Developers
Classifier: License :: OSI Approved :: BSD License
Classifier: Natural Language :: English
Classifier: Programming Language :: Python
